include/glaze/beve.hpp
include/glaze/csv.hpp
include/glaze/eetf.hpp
include/glaze/glaze.hpp
include/glaze/glaze_exceptions.hpp
include/glaze/json.hpp
include/glaze/toml.hpp
include/glaze/version.hpp
include/glaze/api/api.hpp
include/glaze/api/hash.hpp
include/glaze/api/impl.hpp
include/glaze/api/lib.hpp
include/glaze/api/trait.hpp
include/glaze/api/tuplet.hpp
include/glaze/api/type_support.hpp
include/glaze/api/xxh64.hpp
include/glaze/api/std/array.hpp
include/glaze/api/std/deque.hpp
include/glaze/api/std/functional.hpp
include/glaze/api/std/list.hpp
include/glaze/api/std/map.hpp
include/glaze/api/std/optional.hpp
include/glaze/api/std/set.hpp
include/glaze/api/std/shared_ptr.hpp
include/glaze/api/std/span.hpp
include/glaze/api/std/string.hpp
include/glaze/api/std/tuple.hpp
include/glaze/api/std/unique_ptr.hpp
include/glaze/api/std/unordered_map.hpp
include/glaze/api/std/unordered_set.hpp
include/glaze/api/std/variant.hpp
include/glaze/api/std/vector.hpp
include/glaze/base64/base64.hpp
include/glaze/beve/beve_to_json.hpp
include/glaze/beve/header.hpp
include/glaze/beve/key_traits.hpp
include/glaze/beve/ptr.hpp
include/glaze/beve/read.hpp
include/glaze/beve/skip.hpp
include/glaze/beve/wrappers.hpp
include/glaze/beve/write.hpp
include/glaze/compare/approx.hpp
include/glaze/compare/compare.hpp
include/glaze/concepts/container_concepts.hpp
include/glaze/containers/flat_map.hpp
include/glaze/containers/inplace_vector.hpp
include/glaze/core/array_apply.hpp
include/glaze/core/as_array_wrapper.hpp
include/glaze/core/cast.hpp
include/glaze/core/common.hpp
include/glaze/core/constraint.hpp
include/glaze/core/context.hpp
include/glaze/core/convert_struct.hpp
include/glaze/core/custom.hpp
include/glaze/core/error_category.hpp
include/glaze/core/feature_test.hpp
include/glaze/core/manage.hpp
include/glaze/core/meta.hpp
include/glaze/core/opts.hpp
include/glaze/core/ptr.hpp
include/glaze/core/read.hpp
small_cache-0.0.5.dist-info/METADATA
small_cache-0.0.5.dist-info/WHEEL
small_cache-0.0.5.dist-info/RECORD
