Metadata-Version: 2.1
Name: small-cache
Version: 0.0.5
Summary: Small cache
Author: kam1k4dze
Classifier: License :: OSI Approved :: BSD License
Project-URL: Homepage, https://github.com/kam1k4dze/small_cache
Requires-Python: >=3.11
